README.rst
setup.py
bin/sanpai
sanpai/__init__.py
sanpai/san.py
sanpai.egg-info/PKG-INFO
sanpai.egg-info/SOURCES.txt
sanpai.egg-info/dependency_links.txt
sanpai.egg-info/not-zip-safe
sanpai.egg-info/requires.txt
sanpai.egg-info/top_level.txt