Metadata-Version: 1.1
Name: sanpai
Version: 0.1
Summary: sanpai is a tool for inspecting and diffing SANs on x509 certificates
Home-page: http://github.com/blaketmiller/sanpai
Author: Blake Miller
Author-email: blakethomasmiller@gmail.com
License: GNU GPL v2.0
Keywords: x509 cert inspect diff subject alternative name san domain openssl crypto cryptography ssl https
Platform: UNKNOWN
Classifier: Intended Audience :: Developers
Classifier: Intended Audience :: Information Technology
Classifier: License :: OSI Approved :: GNU General Public License v2 (GPLv2)
Classifier: Natural Language :: English
Classifier: Operating System :: POSIX :: Linux
Classifier: Programming Language :: Python :: 2.7
Classifier: Topic :: Software Development :: Testing
Classifier: Topic :: Software Development :: Libraries :: Python Modules
Classifier: Topic :: System :: Filesystems
Classifier: Topic :: Utilities
